{"knowledges": [{"id": "2912_3", "type": "knowledge", "title": null, "header": "assets/topic/asb/1398.png", "content": "Last week I received a lot of letters.", "option": null}, {"id": "2912_4", "type": "knowledge", "title": null, "header": "assets/topic/asb/1399.png", "content": "On Monday my doctor wrote a letter to my teacher.", "option": null}, {"id": "2912_5", "type": "knowledge", "title": null, "header": "assets/topic/asb/1400.png", "content": "Thabisile is sick. She must stay at home.", "option": null}, {"id": "2912_6", "type": "knowledge", "title": null, "header": "assets/topic/asb/1401.png", "content": "On Tuesday I got a letter from my class.", "option": null}, {"id": "2912_7", "type": "knowledge", "title": null, "header": "assets/topic/asb/1402.png", "content": "Get well soon Thabisile!", "option": null}, {"id": "2912_8", "type": "knowledge", "title": null, "header": "assets/topic/asb/1403.png", "content": "On Wednesday I got a letter from my best friend.", "option": null}, {"id": "2912_9", "type": "knowledge", "title": null, "header": "assets/topic/asb/1404.png", "content": "I drew this picture for you. Love from Dudu.", "option": null}, {"id": "2912_10", "type": "knowledge", "title": null, "header": "assets/topic/asb/1405.png", "content": "On Thursday I got a letter from my mother.", "option": null}, {"id": "2912_11", "type": "knowledge", "title": null, "header": null, "content": "You are free to download, copy, translate or adapt this story and use the illustrations as long as you attribute in the following way:\nLetters\nAuthor -\nClare Verbeek, Thembani Dladla and Zanele Buthelezi\nIllustration -\nCathy Feek\nLanguage -\nEnglish\nLevel -\nFirst words\n\u00a9 School of Education and Development (Centre for Adult Education), University of Kwazulu-Natal 2007\nCreative Commons: Attribution-Non Commercial 3.0\nSource\nwww.africanstorybook.org\nOriginal source\nhttp://cae.ukzn.ac.za/resources/seedbooks.aspx", "option": null}], "activities": [{"card": {"id": "2912_12", "type": "activity", "title": "Write a letter to your friend.", "header": "assets/topic/2912.svg", "content": null, "option": null}, "templates": ["assets/topic/2912.svg"]}], "quizzes": [{"id": "2912_13", "type": "oneAtATime", "question": "Whom did the doctor write a letter to?", "header": null, "answers": ["Mother"], "choices": ["Dudu", "Teacher", "Me"]}, {"id": "2912_18", "type": "oneAtATime", "question": "My best friend Dudu wrote a letter on thursday.", "header": null, "answers": ["True."], "choices": ["False."]}, {"id": "2912_21", "type": "open", "question": "Whom do you like to write a letter to?", "header": "assets/topic/asb/1398.png", "answers": [], "choices": ["Friend", "Mother", "Teacher", "Father"]}]}